LICENSE.txt
README.rst
setup.py
linshareapi/__init__.py
linshareapi/cache.py
linshareapi/core.py
linshareapi.egg-info/PKG-INFO
linshareapi.egg-info/SOURCES.txt
linshareapi.egg-info/dependency_links.txt
linshareapi.egg-info/requires.txt
linshareapi.egg-info/top_level.txt
linshareapi/admin/__init__.py
linshareapi/admin/authentication.py
linshareapi/admin/core.py
linshareapi/admin/domainpatterns.py
linshareapi/admin/domainpolicies.py
linshareapi/admin/domains.py
linshareapi/admin/functionalities.py
linshareapi/admin/iusers.py
linshareapi/admin/jwt.py
linshareapi/admin/ldapconnections.py
linshareapi/admin/mail_activations.py
linshareapi/admin/mail_attachments.py
linshareapi/admin/mail_configs.py
linshareapi/admin/public_keys.py
linshareapi/admin/shared_spaces.py
linshareapi/admin/template_api.py
linshareapi/admin/threadmembers.py
linshareapi/admin/threads.py
linshareapi/admin/upgradetasks.py
linshareapi/admin/users.py
linshareapi/admin/welcomemessages.py
linshareapi/user/__init__.py
linshareapi/user/audit.py
linshareapi/user/authentication.py
linshareapi/user/autocomplete.py
linshareapi/user/contactslist.py
linshareapi/user/contactslistcontact.py
linshareapi/user/core.py
linshareapi/user/documents.py
linshareapi/user/guests.py
linshareapi/user/jwt.py
linshareapi/user/rshares.py
linshareapi/user/shared_spaces.py
linshareapi/user/shares.py
linshareapi/user/threadentries.py
linshareapi/user/threadmembers.py
linshareapi/user/threads.py
linshareapi/user/users.py