Metadata-Version: 2.1
Name: linshareapi
Version: 1.0.11
Summary: LinShare api.
Home-page: https://github.com/fred49/linshare-api
Author: Frederic MARTIN
Author-email: frederic.martin.fma@gmail.com
License: GPL3
Platform: UNKNOWN
Classifier: Development Status :: 4 - Beta
Classifier: Intended Audience :: Developers
Classifier: Topic :: Software Development :: Build Tools
Classifier: Environment :: Console
Classifier: License :: OSI Approved :: GNU General Public License v3 (GPLv3)
Classifier: Programming Language :: Python :: 2.6
Classifier: Programming Language :: Python :: 2.7
License-File: LICENSE.txt
